setup.py
django_nav/__init__.py
django_nav/base.py
django_nav/conditionals.py
django_nav.egg-info/PKG-INFO
django_nav.egg-info/SOURCES.txt
django_nav.egg-info/dependency_links.txt
django_nav.egg-info/top_level.txt
django_nav/templatetags/__init__.py
django_nav/templatetags/nav.py