Metadata-Version: 1.0
Name: django-nav
Version: 0.6-beta-2
Summary: An extensible, non intrusive, fast system for generation navigation groupings.
Home-page: http://code.google.com/p/django-nav/
Author: Dj Gilcrease
Author-email: digitalxero@gmail.com
License: UNKNOWN
Download-URL: http://django-nav.googlecode.com/files/django_nav.zip
Keywords: django,navigation,navtree,nav,menu
Platform: UNKNOWN
Classifier: Development Status :: 4 - Beta
Classifier: Environment :: Web Environment
Classifier: Framework :: Django
Classifier: Intended Audience :: Developers
Classifier: License :: OSI Approved :: BSD License
Classifier: Operating System :: OS Independent
Classifier: Programming Language :: Python :: 2
Classifier: Topic :: Internet :: WWW/HTTP
Classifier: Topic :: Internet :: WWW/HTTP :: Dynamic Content
Classifier: Topic :: Software Development :: Libraries :: Python Modules
